spylt/__init__.py
spylt/core.py
spylt/wrappers.py
spylt-0.1.0.post1.dist-info/LICENSE
spylt-0.1.0.post1.dist-info/WHEEL
spylt-0.1.0.post1.dist-info/METADATA
spylt-0.1.0.post1.dist-info/RECORD
